coflow/__init__.py
coflow-0.0.0.dist-info/LICENSE
coflow-0.0.0.dist-info/METADATA
coflow-0.0.0.dist-info/WHEEL
coflow-0.0.0.dist-info/top_level.txt
coflow-0.0.0.dist-info/RECORD
